{"name":"IFix.Core.dll","classes":[{"name":"<Module>","namespace":"","fullName":"<Module>","addr":"0x7602d97ab0","methods":[],"fields":[],"properties":[],"flags":"0x0"},{"name":"IDTagAttribute","namespace":"IFix.Core","fullName":"IFix.Core.IDTagAttribute","addr":"0x7602d97bf0","methods":[{"name":".ctor","rva":"0x370d9e0","addr":"0x768e8319e0","ret":"System.Void","params":[{"name":"id","type":"System.Int32"}]}],"fields":[{"name":"ID","type":"System.Int32","flags":"0x6"}],"properties":[],"flags":"0x100001","parent":"Attribute"},{"name":"<readMethod>c__AnonStorey0","namespace":"","fullName":"<readMethod>c__AnonStorey0","addr":"0x7602d97e00","methods":[{"name":".ctor","rva":"0x3711160","addr":"0x768e835160","ret":"System.Void","params":[]},{"name":"<>m__0","rva":"0x3711d1c","addr":"0x768e835d1c","ret":"System.String","params":[{"name":"m","type":"System.Text.RegularExpressions.Match"}]}],"fields":[{"name":"genericArgInfos","type":"System.Type[]","flags":"0x3"}],"properties":[],"flags":"0x100103","parent":"Object"},{"name":"<Load>c__AnonStorey1","namespace":"","fullName":"<Load>c__AnonStorey1","addr":"0x7602d98190","methods":[{"name":".ctor","rva":"0x3711a40","addr":"0x768e835a40","ret":"System.Void","params":[]}],"fields":[{"name":"nativePointers","type":"System.Collections.Generic.List<System.IntPtr>","flags":"0x3"}],"properties":[],"flags":"0x100103","parent":"Object"},{"name":"<Load>c__AnonStorey2","namespace":"","fullName":"<Load>c__AnonStorey2","addr":"0x7602d98390","methods":[{"name":".ctor","rva":"0x3711a48","addr":"0x768e835a48","ret":"System.Void","params":[]},{"name":"<>m__0","rva":"0x3711d80","addr":"0x768e835d80","ret":"System.Void","params":[]},{"name":"<>m__1","rva":"0x3711e48","addr":"0x768e835e48","ret":"System.Void","params":[]}],"fields":[{"name":"wrapperManager","type":"IFix.Core.WrappersManager","flags":"0x3"},{"name":"<>f__ref$1","type":"IFix.Core.PatchManager.<Load>c__AnonStorey1","flags":"0x3"}],"properties":[],"flags":"0x100103","parent":"Object"},{"name":"PatchManager","namespace":"IFix.Core","fullName":"IFix.Core.PatchManager","addr":"0x7602d97f80","methods":[{"name":"Load","rva":"0x370da08","addr":"0x768e831a08","ret":"IFix.Core.VirtualMachine","params":[{"name":"filepath","type":"System.String"}]},{"name":"readMethod","rva":"0x3710610","addr":"0x768e834610","ret":"System.Reflection.MethodBase","params":[{"name":"reader","type":"System.IO.BinaryReader"},{"name":"externTypes","type":"System.Type[]"}]},{"name":"getRedirectField","rva":"0x3711168","addr":"0x768e835168","ret":"System.Reflection.FieldInfo","params":[{"name":"method","type":"System.Reflection.MethodBase"}]},{"name":"getMapId","rva":"0x3711428","addr":"0x768e835428","ret":"System.Int32","params":[{"name":"idMapArray","type":"System.Collections.Generic.List<System.Type>"},{"name":"method","type":"System.Reflection.MethodBase"}]},{"name":"readSlotInfo","rva":"0x3711710","addr":"0x768e835710","ret":"System.Int32[]","params":[{"name":"reader","type":"System.IO.BinaryReader"},{"name":"itfMethodToId","type":"System.Collections.Generic.Dictionary<System.Reflection.MethodInfo,System.Int32>"},{"name":"externTypes","type":"System.Type[]"},{"name":"maxId","type":"System.Int32"}]},{"name":"Load","rva":"0x370dbb8","addr":"0x768e831bb8","ret":"IFix.Core.VirtualMachine","params":[{"name":"stream","type":"System.IO.Stream"},{"name":"checkNew","type":"System.Boolean"}]},{"name":"Unload","rva":"0x3711aac","addr":"0x768e835aac","ret":"System.Void","params":[{"name":"assembly","type":"System.Reflection.Assembly"}]},{"name":".cctor","rva":"0x3711c68","addr":"0x768e835c68","ret":"System.Void","params":[]},{"name":"<readMethod>m__0","rva":"0x3711d00","addr":"0x768e835d00","ret":"System.Type","params":[{"name":"p","type":"System.Reflection.ParameterInfo"}]}],"fields":[{"name":"removers","type":"System.Collections.Generic.Dictionary<System.Reflection.Assembly,System.Action>","flags":"0x11"},{"name":"<>f__am$cache0","type":"System.Func<System.Reflection.ParameterInfo,System.Type>","flags":"0x11"}],"properties":[],"flags":"0x100181","parent":"Object"},{"name":"<CreateVirtualMachine>c__AnonStorey0","namespace":"","fullName":"<CreateVirtualMachine>c__AnonStorey0","addr":"0x7602db8f50","methods":[{"name":".ctor","rva":"0x37123f0","addr":"0x768e8363f0","ret":"System.Void","params":[]},{"name":"<>m__0","rva":"0x37123f8","addr":"0x768e8363f8","ret":"System.Void","params":[]}],"fields":[{"name":"nativePointers","type":"System.Collections.Generic.List<System.IntPtr>","flags":"0x3"}],"properties":[],"flags":"0x100103","parent":"Object"},{"name":"SimpleVirtualMachineBuilder","namespace":"IFix.Core","fullName":"IFix.Core.SimpleVirtualMachineBuilder","addr":"0x7602db90d0","methods":[{"name":".ctor","rva":"0x3711ef0","addr":"0x768e835ef0","ret":"System.Void","params":[]},{"name":"CreateVirtualMachine","rva":"0x3711ef8","addr":"0x768e835ef8","ret":"IFix.Core.VirtualMachine","params":[{"name":"loopCount","type":"System.Int32"}]}],"fields":[],"properties":[],"flags":"0x100001","parent":"Object"},{"name":"Version","namespace":"IFix","fullName":"IFix.Version","addr":"0x7602db9380","methods":[{"name":".ctor","rva":"0x37124b8","addr":"0x768e8364b8","ret":"System.Void","params":[]}],"fields":[{"name":"FILE_FORMAT","type":"System.String","flags":"0x8056"}],"properties":[],"flags":"0x100001","parent":"Object"},{"name":"Code","namespace":"IFix.Core","fullName":"IFix.Core.Code","addr":"0x760126aa00","methods":[],"fields":[{"name":"value__","type":"System.Int32","flags":"0x606"},{"name":"Stind_R8","type":"IFix.Core.Code","flags":"0x8056"},{"name":"Ldc_I8","type":"IFix.Core.Code","flags":"0x8056"},{"name":"Callvirt","type":"IFix.Core.Code","flags":"0x8056"},{"name":"Sub","type":"IFix.Core.Code","flags":"0x8056"},{"name":"Cgt_Un","type":"IFix.Core.Code","flags":"0x8056"},{"name":"Ldind_I2","type":"IFix.Core.Code","flags":"0x8056"},{"name":"Conv_R4","type":"IFix.Core.Code","flags":"0x8056"},{"name":"Ldftn","type":"IFix.Core.Code","flags":"0x8056"},{"name":"Conv_Ovf_U2","type":"IFix.Core.Code","flags":"0x8056"},{"name":"Conv_U4","type":"IFix.Core.Code","flags":"0x8056"},{"name":"Div_Un","type":"IFix.Core.Code","flags":"0x8056"},{"name":"Stind_I8","type":"IFix.Core.Code","flags":"0x8056"},{"name":"Cpblk","type":"IFix.Core.Code","flags":"0x8056"},{"name":"Bge","type":"IFix.Core.Code","flags":"0x8056"},{"name":"And","type":"IFix.Core.Code","flags":"0x8056"},{"name":"Ldelema","type":"IFix.Core.Code","flags":"0x8056"},{"name":"Ldind_U1","type":"IFix.Core.Code","flags":"0x8056"},{"name":"Readonly","type":"IFix.Core.Code","flags":"0x8056"},{"name":"Rem_Un","type":"IFix.Core.Code","flags":"0x8056"},{"name":"Ldloca","type":"IFix.Core.Code","flags":"0x8056"},{"name":"Conv_Ovf_I1","type":"IFix.Core.Code","flags":"0x8056"},{"name":"Conv_Ovf_I4","type":"IFix.Core.Code","flags":"0x8056"},{"name":"Ldind_I8","type":"IFix.Core.Code","flags":"0x8056"},{"name":"Ldsfld","type":"IFix.Core.Code","flags":"0x8056"},{"name":"Refanyval","type":"IFix.Core.Code","flags":"0x8056"},{"name":"Volatile","type":"IFix.Core.Code","flags":"0x8056"},{"name":"Or","type":"IFix.Core.Code","flags":"0x8056"},{"name":"Mul","type":"IFix.Core.Code","flags":"0x8056"},{"name":"Stelem_R8","type":"IFix.Core.Code","flags":"0x8056"},{"name":"Brfalse","type":"IFix.Core.Code","flags":"0x8056"},{"name":"Bgt","type":"IFix.Core.Code","flags":"0x8056"},{"name":"Stind_Ref","type":"IFix.Core.Code","flags":"0x8056"},{"name":"Ldloc","type":"IFix.Core.Code","flags":"0x8056"},{"name":"Ldarga","type":"IFix.Core.Code","flags":"0x8056"},{"name":"Conv_Ovf_U2_Un","type":"IFix.Core.Code","flags":"0x8056"},{"name":"Initblk","type":"IFix.Core.Code","flags":"0x8056"},{"name":"Conv_I8","type":"IFix.Core.Code","flags":"0x8056"},{"name":"Ble_Un","type":"IFix.Core.Code","flags":"0x8056"},{"name":"Beq","type":"IFix.Core.Code","flags":"0x8056"},{"name":"Shr_Un","type":"IFix.Core.Code","flags":"0x8056"},{"name":"Ldobj","type":"IFix.Core.Code","flags":"0x8056"},{"name":"Unbox_Any","type":"IFix.Core.Code","flags":"0x8056"},{"name":"Ret","type":"IFix.Core.Code","flags":"0x8056"},{"name":"Ldtoken","type":"IFix.Core.Code","flags":"0x8056"},{"name":"Ldvirtftn2","type":"IFix.Core.Code","flags":"0x8056"},{"name":"Ldflda","type":"IFix.Core.Code","flags":"0x8056"},{"name":"Ldelem_R8","type":"IFix.Core.Code","flags":"0x8056"},{"name":"Jmp","type":"IFix.Core.Code","flags":"0x8056"},{"name":"Ldnull","type":"IFix.Core.Code","flags":"0x8056"},{"name":"Tail","type":"IFix.Core.Code","flags":"0x8056"},{"name":"Stind_I4","type":"IFix.Core.Code","flags":"0x8056"},{"name":"Newobj","type":"IFix.Core.Code","flags":"0x8056"},{"name":"Conv_Ovf_U4_Un","type":"IFix.Core.Code","flags":"0x8056"},{"name":"Unaligned","type":"IFix.Core.Code","flags":"0x8056"},{"name":"Ckfinite","type":"IFix.Core.Code","flags":"0x8056"},{"name":"Conv_U2","type":"IFix.Core.Code","flags":"0x8056"},{"name":"Conv_Ovf_I2","type":"IFix.Core.Code","flags":"0x8056"},{"name":"Sizeof","type":"IFix.Core.Code","flags":"0x8056"},{"name":"Ldsflda","type":"IFix.Core.Code","flags":"0x8056"},{"name":"Conv_U8","type":"IFix.Core.Code","flags":"0x8056"},{"name":"Callvirtvirt","type":"IFix.Core.Code","flags":"0x8056"},{"name":"Switch","type":"IFix.Core.Code","flags":"0x8056"},{"name":"Mul_Ovf","type":"IFix.Core.Code","flags":"0x8056"},{"name":"Bne_Un","type":"IFix.Core.Code","flags":"0x8056"},{"name":"Conv_U","type":"IFix.Core.Code","flags":"0x8056"},{"name":"Ldind_Ref","type":"IFix.Core.Code","flags":"0x8056"},{"name":"Conv_Ovf_U1","type":"IFix.Core.Code","flags":"0x8056"},{"name":"Endfinally","type":"IFix.Core.Code","flags":"0x8056"},{"name":"Ldarg","type":"IFix.Core.Code","flags":"0x8056"},{"name":"Nop","type":"IFix.Core.Code","flags":"0x8056"},{"name":"Newanon","type":"IFix.Core.Code","flags":"0x8056"},{"name":"Ldfld","type":"IFix.Core.Code","flags":"0x8056"},{"name":"Stind_I","type":"IFix.Core.Code","flags":"0x8056"},{"name":"Arglist","type":"IFix.Core.Code","flags":"0x8056"},{"name":"Stelem_I2","type":"IFix.Core.Code","flags":"0x8056"},{"name":"Ldelem_I","type":"IFix.Core.Code","flags":"0x8056"},{"name":"Constrained","type":"IFix.Core.Code","flags":"0x8056"},{"name":"Endfilter","type":"IFix.Core.Code","flags":"0x8056"},{"name":"Conv_Ovf_U4","type":"IFix.Core.Code","flags":"0x8056"},{"name":"Ldelem_I4","type":"IFix.Core.Code","flags":"0x8056"},{"name":"Ldtype","type":"IFix.Core.Code","flags":"0x8056"},{"name":"Mkrefany","type":"IFix.Core.Code","flags":"0x8056"},{"name":"Ldind_U4","type":"IFix.Core.Code","flags":"0x8056"},{"name":"Conv_U1","type":"IFix.Core.Code","flags":"0x8056"},{"name":"Conv_Ovf_I2_Un","type":"IFix.Core.Code","flags":"0x8056"},{"name":"Conv_Ovf_U","type":"IFix.Core.Code","flags":"0x8056"},{"name":"Rem","type":"IFix.Core.Code","flags":"0x8056"},{"name":"Ldelem_Any","type":"IFix.Core.Code","flags":"0x8056"},{"name":"Box","type":"IFix.Core.Code","flags":"0x8056"},{"name":"Conv_Ovf_I8","type":"IFix.Core.Code","flags":"0x8056"},{"name":"Castclass","type":"IFix.Core.Code","flags":"0x8056"},{"name":"Conv_Ovf_U_Un","type":"IFix.Core.Code","flags":"0x8056"},{"name":"Conv_Ovf_U8_Un","type":"IFix.Core.Code","flags":"0x8056"},{"name":"Br","type":"IFix.Core.Code","flags":"0x8056"},{"name":"Leave","type":"IFix.Core.Code","flags":"0x8056"},{"name":"Call","type":"IFix.Core.Code","flags":"0x8056"},{"name":"Dup","type":"IFix.Core.Code","flags":"0x8056"},{"name":"Ble","type":"IFix.Core.Code","flags":"0x8056"},{"name":"Sub_Ovf_Un","type":"IFix.Core.Code","flags":"0x8056"},{"name":"Conv_Ovf_I_Un","type":"IFix.Core.Code","flags":"0x8056"},{"name":"Add_Ovf","type":"IFix.Core.Code","flags":"0x8056"},{"name":"Stloc","type":"IFix.Core.Code","flags":"0x8056"},{"name":"Ldc_R4","type":"IFix.Core.Code","flags":"0x8056"},{"name":"Clt_Un","type":"IFix.Core.Code","flags":"0x8056"},{"name":"Cpobj","type":"IFix.Core.Code","flags":"0x8056"},{"name":"Stelem_I8","type":"IFix.Core.Code","flags":"0x8056"},{"name":"Bge_Un","type":"IFix.Core.Code","flags":"0x8056"},{"name":"Conv_Ovf_I8_Un","type":"IFix.Core.Code","flags":"0x8056"},{"name":"Rethrow","type":"IFix.Core.Code","flags":"0x8056"},{"name":"Mul_Ovf_Un","type":"IFix.Core.Code","flags":"0x8056"},{"name":"Cgt","type":"IFix.Core.Code","flags":"0x8056"},{"name":"Ldind_I1","type":"IFix.Core.Code","flags":"0x8056"},{"name":"Ldc_I4","type":"IFix.Core.Code","flags":"0x8056"},{"name":"Conv_I1","type":"IFix.Core.Code","flags":"0x8056"},{"name":"Add","type":"IFix.Core.Code","flags":"0x8056"},{"name":"Ldvirtftn","type":"IFix.Core.Code","flags":"0x8056"},{"name":"Conv_Ovf_I","type":"IFix.Core.Code","flags":"0x8056"},{"name":"Stelem_I","type":"IFix.Core.Code","flags":"0x8056"},{"name":"No","type":"IFix.Core.Code","flags":"0x8056"},{"name":"Refanytype","type":"IFix.Core.Code","flags":"0x8056"},{"name":"Brtrue","type":"IFix.Core.Code","flags":"0x8056"},{"name":"Ceq","type":"IFix.Core.Code","flags":"0x8056"},{"name":"CallExtern","type":"IFix.Core.Code","flags":"0x8056"},{"name":"Isinst","type":"IFix.Core.Code","flags":"0x8056"},{"name":"Break","type":"IFix.Core.Code","flags":"0x8056"},{"name":"Stind_I2","type":"IFix.Core.Code","flags":"0x8056"},{"name":"Ldelem_I2","type":"IFix.Core.Code","flags":"0x8056"},{"name":"Ldind_U2","type":"IFix.Core.Code","flags":"0x8056"},{"name":"Stind_I1","type":"IFix.Core.Code","flags":"0x8056"},{"name":"Ldind_I4","type":"IFix.Core.Code","flags":"0x8056"},{"name":"Stelem_I4","type":"IFix.Core.Code","flags":"0x8056"},{"name":"Stelem_I1","type":"IFix.Core.Code","flags":"0x8056"},{"name":"Stobj","type":"IFix.Core.Code","flags":"0x8056"},{"name":"Conv_I4","type":"IFix.Core.Code","flags":"0x8056"},{"name":"Bgt_Un","type":"IFix.Core.Code","flags":"0x8056"},{"name":"Sub_Ovf","type":"IFix.Core.Code","flags":"0x8056"},{"name":"Add_Ovf_Un","type":"IFix.Core.Code","flags":"0x8056"},{"name":"Ldelem_U4","type":"IFix.Core.Code","flags":"0x8056"},{"name":"Stelem_Any","type":"IFix.Core.Code","flags":"0x8056"},{"name":"Shr","type":"IFix.Core.Code","flags":"0x8056"},{"name":"Not","type":"IFix.Core.Code","flags":"0x8056"},{"name":"Stind_R4","type":"IFix.Core.Code","flags":"0x8056"},{"name":"Conv_Ovf_I1_Un","type":"IFix.Core.Code","flags":"0x8056"},{"name":"Conv_R8","type":"IFix.Core.Code","flags":"0x8056"},{"name":"StackSpace","type":"IFix.Core.Code","flags":"0x8056"},{"name":"Ldelem_U2","type":"IFix.Core.Code","flags":"0x8056"},{"name":"Shl","type":"IFix.Core.Code","flags":"0x8056"},{"name":"Localloc","type":"IFix.Core.Code","flags":"0x8056"},{"name":"Blt","type":"IFix.Core.Code","flags":"0x8056"},{"name":"Ldstr","type":"IFix.Core.Code","flags":"0x8056"},{"name":"Initobj","type":"IFix.Core.Code","flags":"0x8056"},{"name":"Blt_Un","type":"IFix.Core.Code","flags":"0x8056"},{"name":"Ldelem_R4","type":"IFix.Core.Code","flags":"0x8056"},{"name":"Stelem_Ref","type":"IFix.Core.Code","flags":"0x8056"},{"name":"Conv_Ovf_U1_Un","type":"IFix.Core.Code","flags":"0x8056"},{"name":"Ldind_R4","type":"IFix.Core.Code","flags":"0x8056"},{"name":"Div","type":"IFix.Core.Code","flags":"0x8056"},{"name":"Conv_Ovf_U8","type":"IFix.Core.Code","flags":"0x8056"},{"name":"Stsfld","type":"IFix.Core.Code","flags":"0x8056"},{"name":"Pop","type":"IFix.Core.Code","flags":"0x8056"},{"name":"Ldelem_Ref","type":"IFix.Core.Code","flags":"0x8056"},{"name":"Xor","type":"IFix.Core.Code","flags":"0x8056"},{"name":"Conv_I2","type":"IFix.Core.Code","flags":"0x8056"},{"name":"Ldind_I","type":"IFix.Core.Code","flags":"0x8056"},{"name":"Newarr","type":"IFix.Core.Code","flags":"0x8056"},{"name":"Stelem_R4","type":"IFix.Core.Code","flags":"0x8056"},{"name":"Ldc_R8","type":"IFix.Core.Code","flags":"0x8056"},{"name":"Throw","type":"IFix.Core.Code","flags":"0x8056"},{"name":"Ldelem_I8","type":"IFix.Core.Code","flags":"0x8056"},{"name":"Ldelem_I1","type":"IFix.Core.Code","flags":"0x8056"},{"name":"Ldind_R8","type":"IFix.Core.Code","flags":"0x8056"},{"name":"Neg","type":"IFix.Core.Code","flags":"0x8056"},{"name":"Clt","type":"IFix.Core.Code","flags":"0x8056"},{"name":"Conv_R_Un","type":"IFix.Core.Code","flags":"0x8056"},{"name":"Ldelem_U1","type":"IFix.Core.Code","flags":"0x8056"},{"name":"Conv_I","type":"IFix.Core.Code","flags":"0x8056"},{"name":"Starg","type":"IFix.Core.Code","flags":"0x8056"},{"name":"Stfld","type":"IFix.Core.Code","flags":"0x8056"},{"name":"Conv_Ovf_I4_Un","type":"IFix.Core.Code","flags":"0x8056"},{"name":"Ldlen","type":"IFix.Core.Code","flags":"0x8056"},{"name":"Unbox","type":"IFix.Core.Code","flags":"0x8056"}],"properties":[],"flags":"0x101","parent":"Enum"},{"name":"Instruction","namespace":"IFix.Core","fullName":"IFix.Core.Instruction","addr":"0x760126a880","methods":[],"fields":[{"name":"INSTRUCTION_FORMAT_MAGIC","type":"System.UInt64","flags":"0x8056"},{"name":"Code","type":"IFix.Core.Code","flags":"0x6"},{"name":"Operand","type":"System.Int32","flags":"0x6"}],"properties":[],"flags":"0x100109","parent":"ValueType"},{"name":"ExceptionHandlerType","namespace":"IFix.Core","fullName":"IFix.Core.ExceptionHandlerType","addr":"0x7602dbac60","methods":[],"fields":[{"name":"value__","type":"System.Int32","flags":"0x606"},{"name":"Catch","type":"IFix.Core.ExceptionHandlerType","flags":"0x8056"},{"name":"Filter","type":"IFix.Core.ExceptionHandlerType","flags":"0x8056"},{"name":"Finally","type":"IFix.Core.ExceptionHandlerType","flags":"0x8056"},{"name":"Fault","type":"IFix.Core.ExceptionHandlerType","flags":"0x8056"}],"properties":[],"flags":"0x101","parent":"Enum"},{"name":"ExceptionHandler","namespace":"IFix.Core","fullName":"IFix.Core.ExceptionHandler","addr":"0x7602dbb070","methods":[{"name":".ctor","rva":"0x3711a50","addr":"0x768e835a50","ret":"System.Void","params":[]}],"fields":[{"name":"CatchType","type":"System.Type","flags":"0x6"},{"name":"CatchTypeId","type":"System.Int32","flags":"0x6"},{"name":"HandlerEnd","type":"System.Int32","flags":"0x6"},{"name":"HandlerStart","type":"System.Int32","flags":"0x6"},{"name":"HandlerType","type":"IFix.Core.ExceptionHandlerType","flags":"0x6"},{"name":"TryEnd","type":"System.Int32","flags":"0x6"},{"name":"TryStart","type":"System.Int32","flags":"0x6"}],"properties":[],"flags":"0x100101","parent":"Object"},{"name":"AnonymousStorey","namespace":"IFix.Core","fullName":"IFix.Core.AnonymousStorey","addr":"0x7600628e00","methods":[{"name":".ctor","rva":"0x37124c0","addr":"0x768e8364c0","ret":"System.Void","params":[{"name":"fieldNum","type":"System.Int32"},{"name":"fieldTypes","type":"System.Int32[]"},{"name":"typeID","type":"System.Int32"},{"name":"vTable","type":"System.Int32[]"},{"name":"virtualMachine","type":"IFix.Core.VirtualMachine"}]},{"name":"Ldfld","rva":"0x3712728","addr":"0x768e836728","ret":"System.Void","params":[{"name":"fieldIndex","type":"System.Int32"},{"name":"evaluationStackBase","type":"IFix.Core.Value*"},{"name":"evaluationStackPointer","type":"IFix.Core.Value*"},{"name":"managedStack","type":"System.Object[]"}]},{"name":"Stfld","rva":"0x371282c","addr":"0x768e83682c","ret":"System.Void","params":[{"name":"fieldIndex","type":"System.Int32"},{"name":"evaluationStackBase","type":"IFix.Core.Value*"},{"name":"evaluationStackPointer","type":"IFix.Core.Value*"},{"name":"managedStack","type":"System.Object[]"}]},{"name":"Get","rva":"0x371293c","addr":"0x768e83693c","ret":"System.Object","params":[{"name":"fieldIndex","type":"System.Int32"},{"name":"type","type":"System.Type"},{"name":"virtualMachine","type":"IFix.Core.VirtualMachine"},{"name":"valueTypeClone","type":"System.Boolean"}]},{"name":"Set","rva":"0x3713574","addr":"0x768e837574","ret":"System.Void","params":[{"name":"fieldIndex","type":"System.Int32"},{"name":"obj","type":"System.Object"},{"name":"type","type":"System.Type"},{"name":"virtualMachine","type":"IFix.Core.VirtualMachine"}]},{"name":"ObjectEquals","rva":"0x3713880","addr":"0x768e837880","ret":"System.Boolean","params":[{"name":"obj","type":"System.Object"}]},{"name":"Equals","rva":"0x3713888","addr":"0x768e837888","ret":"System.Boolean","params":[{"name":"obj","type":"System.Object"}]},{"name":"ObjectGetHashCode","rva":"0x3713ac8","addr":"0x768e837ac8","ret":"System.Int32","params":[]},{"name":"GetHashCode","rva":"0x3713ad0","addr":"0x768e837ad0","ret":"System.Int32","params":[]},{"name":"ObjectToString","rva":"0x3713b78","addr":"0x768e837b78","ret":"System.String","params":[]},{"name":"ToString","rva":"0x3713b80","addr":"0x768e837b80","ret":"System.String","params":[]},{"name":"Finalize","rva":"0x3713c38","addr":"0x768e837c38","ret":"System.Void","params":[]}],"fields":[{"name":"unmanagedFields","type":"IFix.Core.Value[]","flags":"0x1"},{"name":"managedFields","type":"System.Object[]","flags":"0x1"},{"name":"typeId","type":"System.Int32","flags":"0x3"},{"name":"virtualMachine","type":"IFix.Core.VirtualMachine","flags":"0x4"},{"name":"equalMethodId","type":"System.Int32","flags":"0x1"},{"name":"finalizeMethodId","type":"System.Int32","flags":"0x1"},{"name":"getHashCodeMethodId","type":"System.Int32","flags":"0x1"},{"name":"toStringMethodId","type":"System.Int32","flags":"0x1"}],"properties":[],"flags":"0x100001","parent":"Object"},{"name":"AnonymousStoreyInfo","namespace":"IFix.Core","fullName":"IFix.Core.AnonymousStoreyInfo","addr":"0x7602dbbd70","methods":[{"name":".ctor","rva":"0x3711a60","addr":"0x768e835a60","ret":"System.Void","params":[]}],"fields":[{"name":"FieldNum","type":"System.Int32","flags":"0x6"},{"name":"FieldTypes","type":"System.Int32[]","flags":"0x6"},{"name":"CtorId","type":"System.Int32","flags":"0x6"},{"name":"CtorParamNum","type":"System.Int32","flags":"0x6"},{"name":"Slots","type":"System.Int32[]","flags":"0x6"},{"name":"VTable","type":"System.Int32[]","flags":"0x6"}],"properties":[],"flags":"0x100001","parent":"Object"},{"name":"ValueType","namespace":"IFix.Core","fullName":"IFix.Core.ValueType","addr":"0x7602dbb5d0","methods":[],"fields":[{"name":"value__","type":"System.Int32","flags":"0x606"},{"name":"Integer","type":"IFix.Core.ValueType","flags":"0x8056"},{"name":"Long","type":"IFix.Core.ValueType","flags":"0x8056"},{"name":"Float","type":"IFix.Core.ValueType","flags":"0x8056"},{"name":"Double","type":"IFix.Core.ValueType","flags":"0x8056"},{"name":"StackReference","type":"IFix.Core.ValueType","flags":"0x8056"},{"name":"StaticFieldReference","type":"IFix.Core.ValueType","flags":"0x8056"},{"name":"FieldReference","type":"IFix.Core.ValueType","flags":"0x8056"},{"name":"ChainFieldReference","type":"IFix.Core.ValueType","flags":"0x8056"},{"name":"Object","type":"IFix.Core.ValueType","flags":"0x8056"},{"name":"ValueType","type":"IFix.Core.ValueType","flags":"0x8056"},{"name":"ArrayReference","type":"IFix.Core.ValueType","flags":"0x8056"}],"properties":[],"flags":"0x101","parent":"Enum"},{"name":"Value","namespace":"IFix.Core","fullName":"IFix.Core.Value","addr":"0x7602dbb450","methods":[],"fields":[{"name":"Type","type":"IFix.Core.ValueType","flags":"0x6"},{"name":"Value1","type":"System.Int32","flags":"0x6"},{"name":"Value2","type":"System.Int32","flags":"0x6"}],"properties":[],"flags":"0x100109","parent":"ValueType"},{"name":"<Create>c__AnonStorey0","namespace":"","fullName":"<Create>c__AnonStorey0","addr":"0x7602dbc1b0","methods":[{"name":".ctor","rva":"0x3714ba4","addr":"0x768e838ba4","ret":"System.Void","params":[]}],"fields":[{"name":"delegateType","type":"System.Type","flags":"0x3"}],"properties":[],"flags":"0x100103","parent":"Object"},{"name":"<Create>c__AnonStorey1","namespace":"","fullName":"<Create>c__AnonStorey1","addr":"0x7602dbc4f0","methods":[{"name":".ctor","rva":"0x3714bac","addr":"0x768e838bac","ret":"System.Void","params":[]},{"name":"<>m__0","rva":"0x3714e10","addr":"0x768e838e10","ret":"System.Delegate","params":[{"name":"o","type":"IFix.Core.GenericDelegate"}]}],"fields":[{"name":"methodInfo","type":"System.Reflection.MethodInfo","flags":"0x3"},{"name":"<>f__ref$0","type":"IFix.Core.GenericDelegateFactory.<Create>c__AnonStorey0","flags":"0x3"}],"properties":[],"flags":"0x100103","parent":"Object"},{"name":"<Create>c__AnonStorey2","namespace":"","fullName":"<Create>c__AnonStorey2","addr":"0x7602dbc750","methods":[{"name":".ctor","rva":"0x3714bb4","addr":"0x768e838bb4","ret":"System.Void","params":[]},{"name":"<>m__0","rva":"0x3714e38","addr":"0x768e838e38","ret":"System.Delegate","params":[{"name":"o","type":"IFix.Core.GenericDelegate"}]}],"fields":[{"name":"methodInfo","type":"System.Reflection.MethodInfo","flags":"0x3"},{"name":"<>f__ref$0","type":"IFix.Core.GenericDelegateFactory.<Create>c__AnonStorey0","flags":"0x3"}],"properties":[],"flags":"0x100103","parent":"Object"},{"name":"GenericDelegateFactory","namespace":"IFix.Core","fullName":"IFix.Core.GenericDelegateFactory","addr":"0x7602dbc330","methods":[{"name":".ctor","rva":"0x3713d34","addr":"0x768e837d34","ret":"System.Void","params":[]},{"name":"PreventStripping","rva":"0x3713d3c","addr":"0x768e837d3c","ret":"System.Void","params":[{"name":"obj","type":"System.Object"}]},{"name":"Create","rva":"0x3714020","addr":"0x768e838020","ret":"System.Delegate","params":[{"name":"delegateType","type":"System.Type"},{"name":"virtualMachine","type":"IFix.Core.VirtualMachine"},{"name":"methodId","type":"System.Int32"},{"name":"anonObj","type":"System.Object"}]},{"name":".cctor","rva":"0x3714bbc","addr":"0x768e838bbc","ret":"System.Void","params":[]},{"name":"<Create>m__0","rva":"0x3714c7c","addr":"0x768e838c7c","ret":"System.Boolean","params":[{"name":"m","type":"System.Reflection.MethodInfo"}]},{"name":"<Create>m__1","rva":"0x3714cdc","addr":"0x768e838cdc","ret":"System.Int32","params":[{"name":"m","type":"System.Reflection.MethodInfo"}]},{"name":"<Create>m__2","rva":"0x3714d08","addr":"0x768e838d08","ret":"System.Boolean","params":[{"name":"m","type":"System.Reflection.MethodInfo"}]},{"name":"<Create>m__3","rva":"0x3714d68","addr":"0x768e838d68","ret":"System.Int32","params":[{"name":"m","type":"System.Reflection.MethodInfo"}]},{"name":"<Create>m__4","rva":"0x3714d94","addr":"0x768e838d94","ret":"System.Boolean","params":[{"name":"p","type":"System.Reflection.ParameterInfo"}]},{"name":"<Create>m__5","rva":"0x3714dec","addr":"0x768e838dec","ret":"System.Delegate","params":[{"name":"x","type":"IFix.Core.GenericDelegate"}]},{"name":"<Create>m__6","rva":"0x3714df4","addr":"0x768e838df4","ret":"System.Type","params":[{"name":"pinfo","type":"System.Reflection.ParameterInfo"}]}],"fields":[{"name":"genericAction","type":"System.Reflection.MethodInfo[]","flags":"0x11"},{"name":"genericFunc","type":"System.Reflection.MethodInfo[]","flags":"0x11"},{"name":"genericDelegateCreatorCache","type":"System.Collections.Generic.Dictionary<System.Type,System.Func<IFix.Core.GenericDelegate,System.Delegate>>","flags":"0x11"},{"name":"<>f__am$cache0","type":"System.Func<System.Reflection.MethodInfo,System.Boolean>","flags":"0x11"},{"name":"<>f__am$cache1","type":"System.Func<System.Reflection.MethodInfo,System.Int32>","flags":"0x11"},{"name":"<>f__am$cache2","type":"System.Func<System.Reflection.MethodInfo,System.Boolean>","flags":"0x11"},{"name":"<>f__am$cache3","type":"System.Func<System.Reflection.MethodInfo,System.Int32>","flags":"0x11"},{"name":"<>f__am$cache4","type":"System.Func<System.Reflection.ParameterInfo,System.Boolean>","flags":"0x11"},{"name":"<>f__am$cache5","type":"System.Func<IFix.Core.GenericDelegate,System.Delegate>","flags":"0x11"},{"name":"<>f__am$cache6","type":"System.Func<System.Reflection.ParameterInfo,System.Type>","flags":"0x11"}],"properties":[],"flags":"0x100000","parent":"Object"},{"name":"GenericDelegate","namespace":"IFix.Core","fullName":"IFix.Core.GenericDelegate","addr":"0x765073ce10","methods":[{"name":".ctor","rva":"0x3713f54","addr":"0x768e837f54","ret":"System.Void","params":[{"name":"virtualMachine","type":"IFix.Core.VirtualMachine"},{"name":"methodId","type":"System.Int32"},{"name":"anonObj","type":"System.Object"}]},{"name":"Action","rva":"0x3713fbc","addr":"0x768e837fbc","ret":"System.Void","params":[]},{"name":"Action","rva":"0x193366c","addr":"0x768ca5766c","ret":"System.Void","params":[{"name":"p1","type":"T1"}]},{"name":"Action","rva":"0x193366c","addr":"0x768ca5766c","ret":"System.Void","params":[{"name":"p1","type":"T1"},{"name":"p2","type":"T2"}]},{"name":"Action","rva":"0x193366c","addr":"0x768ca5766c","ret":"System.Void","params":[{"name":"p1","type":"T1"},{"name":"p2","type":"T2"},{"name":"p3","type":"T3"}]},{"name":"Action","rva":"0x193366c","addr":"0x768ca5766c","ret":"System.Void","params":[{"name":"p1","type":"T1"},{"name":"p2","type":"T2"},{"name":"p3","type":"T3"},{"name":"p4","type":"T4"}]},{"name":"Func","rva":"0x193366c","addr":"0x768ca5766c","ret":"TResult","params":[]},{"name":"Func","rva":"0x193366c","addr":"0x768ca5766c","ret":"TResult","params":[{"name":"p1","type":"T1"}]},{"name":"Func","rva":"0x193366c","addr":"0x768ca5766c","ret":"TResult","params":[{"name":"p1","type":"T1"},{"name":"p2","type":"T2"}]},{"name":"Func","rva":"0x193366c","addr":"0x768ca5766c","ret":"TResult","params":[{"name":"p1","type":"T1"},{"name":"p2","type":"T2"},{"name":"p3","type":"T3"}]},{"name":"Func","rva":"0x193366c","addr":"0x768ca5766c","ret":"TResult","params":[{"name":"p1","type":"T1"},{"name":"p2","type":"T2"},{"name":"p3","type":"T3"},{"name":"p4","type":"T4"}]}],"fields":[{"name":"virtualMachine","type":"IFix.Core.VirtualMachine","flags":"0x1"},{"name":"methodId","type":"System.Int32","flags":"0x1"},{"name":"anonObj","type":"System.Object","flags":"0x1"},{"name":"pushSelf","type":"System.Boolean","flags":"0x1"},{"name":"extraArgNum","type":"System.Int32","flags":"0x1"}],"properties":[],"flags":"0x100000","parent":"Object"},{"name":"Option","namespace":"Unity.IL2CPP.CompilerServices","fullName":"Unity.IL2CPP.CompilerServices.Option","addr":"0x7602dbd7d0","methods":[],"fields":[{"name":"value__","type":"System.Int32","flags":"0x606"},{"name":"NullChecks","type":"Unity.IL2CPP.CompilerServices.Option","flags":"0x8056"},{"name":"ArrayBoundsChecks","type":"Unity.IL2CPP.CompilerServices.Option","flags":"0x8056"},{"name":"DivideByZeroChecks","type":"Unity.IL2CPP.CompilerServices.Option","flags":"0x8056"}],"properties":[],"flags":"0x100","parent":"Enum"},{"name":"Il2CppSetOptionAttribute","namespace":"Unity.IL2CPP.CompilerServices","fullName":"Unity.IL2CPP.CompilerServices.Il2CppSetOptionAttribute","addr":"0x7602dbdb30","methods":[{"name":".ctor","rva":"0x3714e60","addr":"0x768e838e60","ret":"System.Void","params":[{"name":"option","type":"Unity.IL2CPP.CompilerServices.Option"},{"name":"value","type":"System.Object"}]},{"name":"get_Option","rva":"0x3714e98","addr":"0x768e838e98","ret":"Unity.IL2CPP.CompilerServices.Option","params":[]},{"name":"set_Option","rva":"0x3714ea0","addr":"0x768e838ea0","ret":"System.Void","params":[{"name":"value","type":"Unity.IL2CPP.CompilerServices.Option"}]},{"name":"get_Value","rva":"0x3714ea8","addr":"0x768e838ea8","ret":"System.Object","params":[]},{"name":"set_Value","rva":"0x3714eb0","addr":"0x768e838eb0","ret":"System.Void","params":[{"name":"value","type":"System.Object"}]}],"fields":[{"name":"<Option>k__BackingField","type":"Unity.IL2CPP.CompilerServices.Option","flags":"0x1"},{"name":"<Value>k__BackingField","type":"System.Object","flags":"0x1"}],"properties":[{"name":"Option"},{"name":"Value"}],"flags":"0x100000","parent":"Attribute"},{"name":"ObjectClone","namespace":"IFix.Core","fullName":"IFix.Core.ObjectClone","addr":"0x7602dbde80","methods":[{"name":".ctor","rva":"0x3714eb8","addr":"0x768e838eb8","ret":"System.Void","params":[]},{"name":"Clone","rva":"0x3714f78","addr":"0x768e838f78","ret":"System.Object","params":[{"name":"obj","type":"System.Object"}]}],"fields":[{"name":"memberwiseClone","type":"System.Reflection.MethodInfo","flags":"0x1"}],"properties":[],"flags":"0x100001","parent":"Object"},{"name":"ReflectionMethodInvoker","namespace":"IFix.Core","fullName":"IFix.Core.ReflectionMethodInvoker","addr":"0x7602dbe0b0","methods":[{"name":".ctor","rva":"0x3714f98","addr":"0x768e838f98","ret":"System.Void","params":[{"name":"method","type":"System.Reflection.MethodBase"}]},{"name":"Invoke","rva":"0x371557c","addr":"0x768e83957c","ret":"System.Void","params":[{"name":"virtualMachine","type":"IFix.Core.VirtualMachine"},{"name":"call","type":"IFix.Core.Call&"},{"name":"isInstantiate","type":"System.Boolean"}]}],"fields":[{"name":"paramCount","type":"System.Int32","flags":"0x1"},{"name":"hasThis","type":"System.Boolean","flags":"0x1"},{"name":"hasReturn","type":"System.Boolean","flags":"0x1"},{"name":"refFlags","type":"System.Boolean[]","flags":"0x1"},{"name":"outFlags","type":"System.Boolean[]","flags":"0x1"},{"name":"rawTypes","type":"System.Type[]","flags":"0x1"},{"name":"method","type":"System.Reflection.MethodBase","flags":"0x1"},{"name":"ctor","type":"System.Reflection.ConstructorInfo","flags":"0x1"},{"name":"returnType","type":"System.Type","flags":"0x1"},{"name":"isNullableHasValue","type":"System.Boolean","flags":"0x1"},{"name":"isNullableValue","type":"System.Boolean","flags":"0x1"}],"properties":[],"flags":"0x100000","parent":"Object"},{"name":"UnmanagedStack","namespace":"IFix.Core","fullName":"IFix.Core.UnmanagedStack","addr":"0x7602dbe4f0","methods":[],"fields":[{"name":"Base","type":"IFix.Core.Value*","flags":"0x6"},{"name":"Top","type":"IFix.Core.Value*","flags":"0x6"}],"properties":[],"flags":"0x100108","parent":"ValueType"},{"name":"ThreadStackInfo","namespace":"IFix.Core","fullName":"IFix.Core.ThreadStackInfo","addr":"0x7602dbe6b0","methods":[{"name":".ctor","rva":"0x3715d78","addr":"0x768e839d78","ret":"System.Void","params":[]},{"name":"get_Stack","rva":"0x3715e34","addr":"0x768e839e34","ret":"IFix.Core.ThreadStackInfo","params":[]},{"name":".cctor","rva":"0x3715f48","addr":"0x768e839f48","ret":"System.Void","params":[]}],"fields":[{"name":"UnmanagedStack","type":"IFix.Core.UnmanagedStack*","flags":"0x6"},{"name":"ManagedStack","type":"System.Object[]","flags":"0x6"},{"name":"evaluationStackHandler","type":"System.IntPtr","flags":"0x1"},{"name":"unmanagedStackHandler","type":"System.IntPtr","flags":"0x1"},{"name":"localSlot","type":"System.LocalDataStoreSlot","flags":"0x11"}],"properties":[{"name":"Stack"}],"flags":"0x100000","parent":"Object"},{"name":"EvaluationStackOperation","namespace":"IFix.Core","fullName":"IFix.Core.EvaluationStackOperation","addr":"0x7602dbe9c0","methods":[{"name":"UnboxPrimitive","rva":"0x3715fa4","addr":"0x768e839fa4","ret":"System.Void","params":[{"name":"evaluationStackPointer","type":"IFix.Core.Value*"},{"name":"obj","type":"System.Object"},{"name":"type","type":"System.Type"}]},{"name":"mGet","rva":"0x3716580","addr":"0x768e83a580","ret":"System.Object","params":[{"name":"isArray","type":"System.Boolean"},{"name":"root","type":"System.Object"},{"name":"layer","type":"System.Int32"},{"name":"fieldIdList","type":"System.Int32[]"},{"name":"fieldInfos","type":"System.Reflection.FieldInfo[]"},{"name":"newFieldInfos","type":"System.Collections.Generic.Dictionary<System.Int32,IFix.Core.NewFieldInfo>"}]},{"name":"mSet","rva":"0x3716898","addr":"0x768e83a898","ret":"System.Void","params":[{"name":"isArray","type":"System.Boolean"},{"name":"root","type":"System.Object"},{"name":"val","type":"System.Object"},{"name":"layer","type":"System.Int32"},{"name":"fieldIdList","type":"System.Int32[]"},{"name":"fieldInfos","type":"System.Reflection.FieldInfo[]"},{"name":"newFieldInfos","type":"System.Collections.Generic.Dictionary<System.Int32,IFix.Core.NewFieldInfo>"}]},{"name":"ToObject","rva":"0x3712984","addr":"0x768e836984","ret":"System.Object","params":[{"name":"evaluationStackBase","type":"IFix.Core.Value*"},{"name":"evaluationStackPointer","type":"IFix.Core.Value*"},{"name":"managedStack","type":"System.Object[]"},{"name":"type","type":"System.Type"},{"name":"virtualMachine","type":"IFix.Core.VirtualMachine"},{"name":"valueTypeClone","type":"System.Boolean"}]},{"name":"PushObject","rva":"0x37135b0","addr":"0x768e8375b0","ret":"System.Void","params":[{"name":"evaluationStackBase","type":"IFix.Core.Value*"},{"name":"evaluationStackPointer","type":"IFix.Core.Value*"},{"name":"managedStack","type":"System.Object[]"},{"name":"obj","type":"System.Object"},{"name":"type","type":"System.Type"}]},{"name":"UpdateReference","rva":"0x3716db8","addr":"0x768e83adb8","ret":"System.Void","params":[{"name":"evaluationStackBase","type":"IFix.Core.Value*"},{"name":"evaluationStackPointer","type":"IFix.Core.Value*"},{"name":"managedStack","type":"System.Object[]"},{"name":"obj","type":"System.Object"},{"name":"virtualMachine","type":"IFix.Core.VirtualMachine"},{"name":"type","type":"System.Type"}]}],"fields":[],"properties":[],"flags":"0x100180","parent":"Object"},{"name":"Call","namespace":"IFix.Core","fullName":"IFix.Core.Call","addr":"0x7650737d70","methods":[{"name":"Begin","rva":"0x3713934","addr":"0x768e837934","ret":"IFix.Core.Call","params":[]},{"name":"BeginForStack","rva":"0x37171d8","addr":"0x768e83b1d8","ret":"IFix.Core.Call","params":[{"name":"stack","type":"IFix.Core.ThreadStackInfo"}]},{"name":"PushBoolean","rva":"0x3717250","addr":"0x768e83b250","ret":"System.Void","params":[{"name":"b","type":"System.Boolean"}]},{"name":"GetBoolean","rva":"0x3713a9c","addr":"0x768e837a9c","ret":"System.Boolean","params":[{"name":"offset","type":"System.Int32"}]},{"name":"PushByte","rva":"0x3717278","addr":"0x768e83b278","ret":"System.Void","params":[{"name":"b","type":"System.Byte"}]},{"name":"GetByte","rva":"0x37172c0","addr":"0x768e83b2c0","ret":"System.Byte","params":[{"name":"offset","type":"System.Int32"}]},{"name":"PushSByte","rva":"0x37172e4","addr":"0x768e83b2e4","ret":"System.Void","params":[{"name":"sb","type":"System.SByte"}]},{"name":"GetSByte","rva":"0x371730c","addr":"0x768e83b30c","ret":"System.SByte","params":[{"name":"offset","type":"System.Int32"}]},{"name":"PushInt16","rva":"0x3717330","addr":"0x768e83b330","ret":"System.Void","params":[{"name":"s","type":"System.Int16"}]},{"name":"GetInt16","rva":"0x3717358","addr":"0x768e83b358","ret":"System.Int16","params":[{"name":"offset","type":"System.Int32"}]},{"name":"PushChar","rva":"0x371737c","addr":"0x768e83b37c","ret":"System.Void","params":[{"name":"c","type":"System.Char"}]},{"name":"GetChar","rva":"0x37173a4","addr":"0x768e83b3a4","ret":"System.Char","params":[{"name":"offset","type":"System.Int32"}]},{"name":"PushUInt16","rva":"0x37173c8","addr":"0x768e83b3c8","ret":"System.Void","params":[{"name":"us","type":"System.UInt16"}]},{"name":"GetUInt16","rva":"0x37173f0","addr":"0x768e83b3f0","ret":"System.UInt16","params":[{"name":"offset","type":"System.Int32"}]},{"name":"PushInt32","rva":"0x37172a0","addr":"0x768e83b2a0","ret":"System.Void","params":[{"name":"i","type":"System.Int32"}]},{"name":"GetInt32","rva":"0x3713b54","addr":"0x768e837b54","ret":"System.Int32","params":[{"name":"offset","type":"System.Int32"}]},{"name":"PushUInt32","rva":"0x3717414","addr":"0x768e83b414","ret":"System.Void","params":[{"name":"ui","type":"System.UInt32"}]},{"name":"GetUInt32","rva":"0x3717434","addr":"0x768e83b434","ret":"System.UInt32","params":[{"name":"offset","type":"System.Int32"}]},{"name":"PushInt64","rva":"0x3717458","addr":"0x768e83b458","ret":"System.Void","params":[{"name":"i","type":"System.Int64"}]},{"name":"GetInt64","rva":"0x3717484","addr":"0x768e83b484","ret":"System.Int64","params":[{"name":"offset","type":"System.Int32"}]},{"name":"PushUInt64","rva":"0x37174a8","addr":"0x768e83b4a8","ret":"System.Void","params":[{"name":"i","type":"System.UInt64"}]},{"name":"GetUInt64","rva":"0x37174d4","addr":"0x768e83b4d4","ret":"System.UInt64","params":[{"name":"offset","type":"System.Int32"}]},{"name":"PushSingle","rva":"0x37174f8","addr":"0x768e83b4f8","ret":"System.Void","params":[{"name":"f","type":"System.Single"}]},{"name":"GetSingle","rva":"0x3717524","addr":"0x768e83b524","ret":"System.Single","params":[{"name":"offset","type":"System.Int32"}]},{"name":"PushDouble","rva":"0x3717548","addr":"0x768e83b548","ret":"System.Void","params":[{"name":"d","type":"System.Double"}]},{"name":"GetDouble","rva":"0x3717574","addr":"0x768e83b574","ret":"System.Double","params":[{"name":"offset","type":"System.Int32"}]},{"name":"PushIntPtr","rva":"0x3717598","addr":"0x768e83b598","ret":"System.Void","params":[{"name":"i","type":"System.IntPtr"}]},{"name":"GetIntPtr","rva":"0x37175e0","addr":"0x768e83b5e0","ret":"System.IntPtr","params":[{"name":"offset","type":"System.Int32"}]},{"name":"PushUIntPtr","rva":"0x3717618","addr":"0x768e83b618","ret":"System.Void","params":[{"name":"i","type":"System.UIntPtr"}]},{"name":"GetUIntPtr","rva":"0x3717660","addr":"0x768e83b660","ret":"System.UIntPtr","params":[{"name":"offset","type":"System.Int32"}]},{"name":"PushObject","rva":"0x37139e8","addr":"0x768e8379e8","ret":"System.Void","params":[{"name":"o","type":"System.Object"}]},{"name":"PushValueType","rva":"0x3717698","addr":"0x768e83b698","ret":"System.Void","params":[{"name":"o","type":"System.Object"}]},{"name":"GetObject","rva":"0x371774c","addr":"0x768e83b74c","ret":"System.Object","params":[{"name":"offset","type":"System.Int32"}]},{"name":"GetAsType","rva":"0x193366c","addr":"0x768ca5766c","ret":"T","params":[{"name":"offset","type":"System.Int32"}]},{"name":"PushObjectAsResult","rva":"0x3715d40","addr":"0x768e839d40","ret":"System.Void","params":[{"name":"obj","type":"System.Object"},{"name":"type","type":"System.Type"}]},{"name":"PushRef","rva":"0x37177fc","addr":"0x768e83b7fc","ret":"System.Void","params":[{"name":"offset","type":"System.Int32"}]},{"name":"UpdateReference","rva":"0x3715c9c","addr":"0x768e839c9c","ret":"System.Void","params":[{"name":"offset","type":"System.Int32"},{"name":"obj","type":"System.Object"},{"name":"virtualMachine","type":"IFix.Core.VirtualMachine"},{"name":"type","type":"System.Type"}]},{"name":"End","rva":"0x3717834","addr":"0x768e83b834","ret":"System.Void","params":[{"name":"call","type":"IFix.Core.Call&"}]}],"fields":[{"name":"argumentBase","type":"IFix.Core.Value*","flags":"0x3"},{"name":"evaluationStackBase","type":"IFix.Core.Value*","flags":"0x3"},{"name":"managedStack","type":"System.Object[]","flags":"0x3"},{"name":"currentTop","type":"IFix.Core.Value*","flags":"0x3"},{"name":"topWriteBack","type":"IFix.Core.Value**","flags":"0x3"}],"properties":[],"flags":"0x100109","parent":"ValueType"},{"name":"InterpretAttribute","namespace":"IFix","fullName":"IFix.InterpretAttribute","addr":"0x7602dbfe90","methods":[{"name":".ctor","rva":"0x3717838","addr":"0x768e83b838","ret":"System.Void","params":[{"name":"version","type":"System.Int32"}]}],"fields":[{"name":"version","type":"System.Int32","flags":"0x6"}],"properties":[],"flags":"0x100001","parent":"Attribute"},{"name":"PatchAttribute","namespace":"IFix","fullName":"IFix.PatchAttribute","addr":"0x7602dc00a0","methods":[{"name":".ctor","rva":"0x3717860","addr":"0x768e83b860","ret":"System.Void","params":[{"name":"version","type":"System.Int32"}]}],"fields":[{"name":"version","type":"System.Int32","flags":"0x6"}],"properties":[],"flags":"0x100001","parent":"Attribute"},{"name":"CustomBridgeAttribute","namespace":"IFix","fullName":"IFix.CustomBridgeAttribute","addr":"0x7602dc02b0","methods":[{"name":".ctor","rva":"0x3717888","addr":"0x768e83b888","ret":"System.Void","params":[]}],"fields":[],"properties":[],"flags":"0x100001","parent":"Attribute"},{"name":"Utils","namespace":"IFix.Core","fullName":"IFix.Core.Utils","addr":"0x7602dc0480","methods":[{"name":"IsAssignable","rva":"0x3717890","addr":"0x768e83b890","ret":"System.Boolean","params":[{"name":"delegateMethod","type":"System.Reflection.MethodInfo"},{"name":"method","type":"System.Reflection.MethodInfo"}]},{"name":"TryAdapterToDelegate","rva":"0x3717aac","addr":"0x768e83baac","ret":"System.Delegate","params":[{"name":"obj","type":"System.Object"},{"name":"delegateType","type":"System.Type"},{"name":"perfix","type":"System.String"}]},{"name":".cctor","rva":"0x3717cd0","addr":"0x768e83bcd0","ret":"System.Void","params":[]}],"fields":[{"name":"delegateAdptCache","type":"System.Collections.Generic.Dictionary<System.Type,System.Reflection.MethodInfo>","flags":"0x11"}],"properties":[],"flags":"0x100181","parent":"Object"},{"name":"RuntimeException","namespace":"IFix.Core","fullName":"IFix.Core.RuntimeException","addr":"0x7602dc0820","methods":[{"name":".ctor","rva":"0x3717d68","addr":"0x768e83bd68","ret":"System.Void","params":[]},{"name":"get_Real","rva":"0x3717dc0","addr":"0x768e83bdc0","ret":"System.Exception","params":[]},{"name":"set_Real","rva":"0x3717dc8","addr":"0x768e83bdc8","ret":"System.Void","params":[{"name":"value","type":"System.Exception"}]}],"fields":[{"name":"<Real>k__BackingField","type":"System.Exception","flags":"0x1"}],"properties":[{"name":"Real"}],"flags":"0x100000","parent":"Exception"},{"name":"ExternInvoker","namespace":"IFix.Core","fullName":"IFix.Core.ExternInvoker","addr":"0x7602dc0ae0","methods":[{"name":".ctor","rva":"0x3717dd0","addr":"0x768e83bdd0","ret":"System.Void","params":[{"name":"object","type":"System.Object"},{"name":"method","type":"System.IntPtr"}]},{"name":"Invoke","rva":"0x3717edc","addr":"0x768e83bedc","ret":"System.Void","params":[{"name":"vm","type":"IFix.Core.VirtualMachine"},{"name":"call","type":"IFix.Core.Call&"},{"name":"isInstantiate","type":"System.Boolean"}]},{"name":"BeginInvoke","rva":"0x3717ef4","addr":"0x768e83bef4","ret":"System.IAsyncResult","params":[{"name":"vm","type":"IFix.Core.VirtualMachine"},{"name":"call","type":"IFix.Core.Call&"},{"name":"isInstantiate","type":"System.Boolean"},{"name":"callback","type":"System.AsyncCallback"},{"name":"object","type":"System.Object"}]},{"name":"EndInvoke","rva":"0x3717fc0","addr":"0x768e83bfc0","ret":"System.Void","params":[{"name":"call","type":"IFix.Core.Call&"},{"name":"result","type":"System.IAsyncResult"}]}],"fields":[],"properties":[],"flags":"0x101","parent":"MulticastDelegate"},{"name":"FieldAddr","namespace":"IFix.Core","fullName":"IFix.Core.FieldAddr","addr":"0x7602dc0f80","methods":[{"name":".ctor","rva":"0x3717fdc","addr":"0x768e83bfdc","ret":"System.Void","params":[]}],"fields":[{"name":"Object","type":"System.Object","flags":"0x6"},{"name":"FieldIdList","type":"System.Int32[]","flags":"0x6"}],"properties":[],"flags":"0x100000","parent":"Object"},{"name":"Cleanner","namespace":"IFix.Core","fullName":"IFix.Core.Cleanner","addr":"0x7602dc1160","methods":[{"name":".ctor","rva":"0x3717fe4","addr":"0x768e83bfe4","ret":"System.Void","params":[]},{"name":"Start","rva":"0x3717fec","addr":"0x768e83bfec","ret":"System.Void","params":[]},{"name":"Stop","rva":"0x3718078","addr":"0x768e83c078","ret":"System.Void","params":[]},{"name":"Finalize","rva":"0x37180d0","addr":"0x768e83c0d0","ret":"System.Void","params":[]},{"name":".cctor","rva":"0x3718428","addr":"0x768e83c428","ret":"System.Void","params":[]}],"fields":[{"name":"start","type":"System.Boolean","flags":"0x11"}],"properties":[],"flags":"0x100001","parent":"Object"},{"name":"NewFieldInfo","namespace":"IFix.Core","fullName":"IFix.Core.NewFieldInfo","addr":"0x7602dbed20","methods":[{"name":".ctor","rva":"0x3711a58","addr":"0x768e835a58","ret":"System.Void","params":[]},{"name":"SetDefaultValue","rva":"0x3718470","addr":"0x768e83c470","ret":"System.Object","params":[{"name":"obj","type":"System.Object"}]},{"name":"Sweep","rva":"0x37181e4","addr":"0x768e83c1e4","ret":"System.Void","params":[]},{"name":"CheckInit","rva":"0x3716cd8","addr":"0x768e83acd8","ret":"System.Void","params":[{"name":"virtualMachine","type":"IFix.Core.VirtualMachine"},{"name":"obj","type":"System.Object"}]},{"name":"ObjectToIndex","rva":"0x37185ec","addr":"0x768e83c5ec","ret":"System.Int32","params":[{"name":"obj","type":"System.Object"}]},{"name":"HasInitialize","rva":"0x37184cc","addr":"0x768e83c4cc","ret":"System.Boolean","params":[{"name":"obj","type":"System.Object"}]},{"name":"GetValue","rva":"0x371679c","addr":"0x768e83a79c","ret":"System.Object","params":[{"name":"obj","type":"System.Object"}]},{"name":"SetValue","rva":"0x3716ac8","addr":"0x768e83aac8","ret":"System.Void","params":[{"name":"obj","type":"System.Object"},{"name":"value","type":"System.Object"}]},{"name":".cctor","rva":"0x3718664","addr":"0x768e83c664","ret":"System.Void","params":[]}],"fields":[{"name":"Name","type":"System.String","flags":"0x6"},{"name":"DeclaringType","type":"System.Type","flags":"0x6"},{"name":"FieldType","type":"System.Type","flags":"0x6"},{"name":"MethodId","type":"System.Int32","flags":"0x6"},{"name":"staticObjectKey","type":"System.Int32","flags":"0x31"},{"name":"stack","type":"IFix.Core.ThreadStackInfo","flags":"0x31"},{"name":"newFieldValues","type":"System.Collections.Generic.Dictionary<System.Int32,System.Collections.Generic.Dictionary<System.String,System.Object>>","flags":"0x31"},{"name":"objList","type":"System.Collections.Generic.Dictionary<System.Int32,System.WeakReference>","flags":"0x31"}],"properties":[],"flags":"0x100001","parent":"Object"},{"name":"VirtualMachine","namespace":"IFix.Core","fullName":"IFix.Core.VirtualMachine","addr":"0x760126a700","methods":[{"name":".ctor","rva":"0x3700750","addr":"0x768e824750","ret":"System.Void","params":[{"name":"unmanaged_codes","type":"IFix.Core.Instruction**"},{"name":"on_dispose","type":"System.Action"}]},{"name":"get_ExceptionHandlers","rva":"0x3700868","addr":"0x768e824868","ret":"IFix.Core.ExceptionHandler[][]","params":[]},{"name":"set_ExceptionHandlers","rva":"0x3700870","addr":"0x768e824870","ret":"System.Void","params":[{"name":"value","type":"IFix.Core.ExceptionHandler[][]"}]},{"name":"get_ExternTypes","rva":"0x3700878","addr":"0x768e824878","ret":"System.Type[]","params":[]},{"name":"set_ExternTypes","rva":"0x3700880","addr":"0x768e824880","ret":"System.Void","params":[{"name":"value","type":"System.Type[]"}]},{"name":"get_ExternMethods","rva":"0x3700888","addr":"0x768e824888","ret":"System.Reflection.MethodBase[]","params":[]},{"name":"set_ExternMethods","rva":"0x3700890","addr":"0x768e824890","ret":"System.Void","params":[{"name":"value","type":"System.Reflection.MethodBase[]"}]},{"name":"get_InternStrings","rva":"0x370090c","addr":"0x768e82490c","ret":"System.String[]","params":[]},{"name":"set_InternStrings","rva":"0x3700914","addr":"0x768e824914","ret":"System.Void","params":[{"name":"value","type":"System.String[]"}]},{"name":"get_FieldInfos","rva":"0x370091c","addr":"0x768e82491c","ret":"System.Reflection.FieldInfo[]","params":[]},{"name":"set_FieldInfos","rva":"0x3700924","addr":"0x768e824924","ret":"System.Void","params":[{"name":"value","type":"System.Reflection.FieldInfo[]"}]},{"name":"get_NewFieldInfos","rva":"0x370092c","addr":"0x768e82492c","ret":"System.Collections.Generic.Dictionary<System.Int32,IFix.Core.NewFieldInfo>","params":[]},{"name":"set_NewFieldInfos","rva":"0x3700934","addr":"0x768e824934","ret":"System.Void","params":[{"name":"value","type":"System.Collections.Generic.Dictionary<System.Int32,IFix.Core.NewFieldInfo>"}]},{"name":"get_AnonymousStoreyInfos","rva":"0x370093c","addr":"0x768e82493c","ret":"IFix.Core.AnonymousStoreyInfo[]","params":[]},{"name":"set_AnonymousStoreyInfos","rva":"0x3700944","addr":"0x768e824944","ret":"System.Void","params":[{"name":"value","type":"IFix.Core.AnonymousStoreyInfo[]"}]},{"name":"get_StaticFieldTypes","rva":"0x370094c","addr":"0x768e82494c","ret":"System.Type[]","params":[]},{"name":"set_StaticFieldTypes","rva":"0x3700954","addr":"0x768e824954","ret":"System.Void","params":[{"name":"value","type":"System.Type[]"}]},{"name":"get_Cctors","rva":"0x37009d4","addr":"0x768e8249d4","ret":"System.Int32[]","params":[]},{"name":"set_Cctors","rva":"0x37009dc","addr":"0x768e8249dc","ret":"System.Void","params":[{"name":"value","type":"System.Int32[]"}]},{"name":"get_WrappersManager","rva":"0x37009e4","addr":"0x768e8249e4","ret":"IFix.Core.WrappersManager","params":[]},{"name":"set_WrappersManager","rva":"0x37009ec","addr":"0x768e8249ec","ret":"System.Void","params":[{"name":"value","type":"IFix.Core.WrappersManager"}]},{"name":"Finalize","rva":"0x37009f4","addr":"0x768e8249f4","ret":"System.Void","params":[]},{"name":"checkCctorExecute","rva":"0x3700ae4","addr":"0x768e824ae4","ret":"System.Void","params":[{"name":"fieldId","type":"System.Int32"},{"name":"argumentBase","type":"IFix.Core.Value*"},{"name":"managedStack","type":"System.Object[]"},{"name":"evaluationStackBase","type":"IFix.Core.Value*"}]},{"name":"store","rva":"0x3700b94","addr":"0x768e824b94","ret":"System.Void","params":[{"name":"stackBase","type":"IFix.Core.Value*"},{"name":"dst","type":"IFix.Core.Value*"},{"name":"src","type":"IFix.Core.Value*"},{"name":"managedStack","type":"System.Object[]"}]},{"name":"copy","rva":"0x3700cf4","addr":"0x768e824cf4","ret":"System.Void","params":[{"name":"stackBase","type":"IFix.Core.Value*"},{"name":"dst","type":"IFix.Core.Value*"},{"name":"src","type":"IFix.Core.Value*"},{"name":"managedStack","type":"System.Object[]"}]},{"name":"Execute","rva":"0x3700e50","addr":"0x768e824e50","ret":"System.Void","params":[{"name":"methodIndex","type":"System.Int32"},{"name":"call","type":"IFix.Core.Call&"},{"name":"argsCount","type":"System.Int32"},{"name":"refCount","type":"System.Int32"}]},{"name":"Execute","rva":"0x3700b68","addr":"0x768e824b68","ret":"IFix.Core.Value*","params":[{"name":"methodIndex","type":"System.Int32"},{"name":"argumentBase","type":"IFix.Core.Value*"},{"name":"managedStack","type":"System.Object[]"},{"name":"evaluationStackBase","type":"IFix.Core.Value*"},{"name":"argsCount","type":"System.Int32"}]},{"name":"printStack","rva":"0x370c7f0","addr":"0x768e8307f0","ret":"System.Void","params":[{"name":"title","type":"System.String"},{"name":"val","type":"IFix.Core.Value*"}]},{"name":"throwRuntimeException","rva":"0x370ca3c","addr":"0x768e830a3c","ret":"System.Void","params":[{"name":"e","type":"System.Exception"},{"name":"bWrap","type":"System.Boolean"}]},{"name":"getExceptionHandler","rva":"0x370cab0","addr":"0x768e830ab0","ret":"IFix.Core.ExceptionHandler","params":[{"name":"methodIndex","type":"System.Int32"},{"name":"exceptionType","type":"System.Type"},{"name":"pc","type":"System.Int32"}]},{"name":"arrayGet","rva":"0x370cb80","addr":"0x768e830b80","ret":"System.Void","params":[{"name":"obj","type":"System.Object"},{"name":"idx","type":"System.Int32"},{"name":"val","type":"IFix.Core.Value*"},{"name":"managedStack","type":"System.Object[]"},{"name":"evaluationStackBase","type":"IFix.Core.Value*"}]},{"name":"arraySet","rva":"0x370cf40","addr":"0x768e830f40","ret":"System.Void","params":[{"name":"obj","type":"System.Object"},{"name":"idx","type":"System.Int32"},{"name":"val","type":"IFix.Core.Value*"},{"name":"managedStack","type":"System.Object[]"},{"name":"evaluationStackBase","type":"IFix.Core.Value*"}]},{"name":"_Info","rva":"0x370d2d8","addr":"0x768e8312d8","ret":"System.Void","params":[{"name":"a","type":"System.String"}]},{"name":"Execute","rva":"0x3700e94","addr":"0x768e824e94","ret":"IFix.Core.Value*","params":[{"name":"pc","type":"IFix.Core.Instruction*"},{"name":"argumentBase","type":"IFix.Core.Value*"},{"name":"managedStack","type":"System.Object[]"},{"name":"evaluationStackBase","type":"IFix.Core.Value*"},{"name":"argsCount","type":"System.Int32"},{"name":"methodIndex","type":"System.Int32"},{"name":"refCount","type":"System.Int32"},{"name":"topWriteBack","type":"IFix.Core.Value**"}]},{"name":"Sweep","rva":"0x370d374","addr":"0x768e831374","ret":"System.Void","params":[]},{"name":"Statistics","rva":"0x370d3c4","addr":"0x768e8313c4","ret":"System.String","params":[]},{"name":"SetGlobal","rva":"0x370d790","addr":"0x768e831790","ret":"System.Void","params":[{"name":"virtualMachine","type":"IFix.Core.VirtualMachine"},{"name":"throwWhileExisted","type":"System.Boolean"}]},{"name":"InitializeGlobal","rva":"0x370d7c8","addr":"0x768e8317c8","ret":"System.Void","params":[{"name":"stream","type":"System.IO.Stream"}]},{"name":"ReplaceGlobal","rva":"0x370d824","addr":"0x768e831824","ret":"System.Void","params":[{"name":"stream","type":"System.IO.Stream"}]},{"name":"RemoveGlobal","rva":"0x370d880","addr":"0x768e831880","ret":"System.Void","params":[]},{"name":"GetGlobal","rva":"0x370d8e4","addr":"0x768e8318e4","ret":"IFix.Core.VirtualMachine","params":[]},{"name":".cctor","rva":"0x370d91c","addr":"0x768e83191c","ret":"System.Void","params":[]}],"fields":[{"name":"tellUnity4IncludeInstructionFisrt","type":"IFix.Core.Instruction","flags":"0x1"},{"name":"MAX_EVALUATION_STACK_SIZE","type":"System.Int32","flags":"0x8056"},{"name":"objectClone","type":"IFix.Core.ObjectClone","flags":"0x3"},{"name":"unmanagedCodes","type":"IFix.Core.Instruction**","flags":"0x1"},{"name":"exceptionHandlers","type":"IFix.Core.ExceptionHandler[][]","flags":"0x1"},{"name":"onDispose","type":"System.Action","flags":"0x1"},{"name":"externInvokers","type":"IFix.Core.ExternInvoker[]","flags":"0x1"},{"name":"externMethods","type":"System.Reflection.MethodBase[]","flags":"0x1"},{"name":"externTypes","type":"System.Type[]","flags":"0x1"},{"name":"internStrings","type":"System.String[]","flags":"0x1"},{"name":"fieldInfos","type":"System.Reflection.FieldInfo[]","flags":"0x3"},{"name":"newFieldInfos","type":"System.Collections.Generic.Dictionary<System.Int32,IFix.Core.NewFieldInfo>","flags":"0x3"},{"name":"anonymousStoreyInfos","type":"IFix.Core.AnonymousStoreyInfo[]","flags":"0x1"},{"name":"overrideCache","type":"System.Collections.Generic.Dictionary<System.Type,System.Collections.Generic.Dictionary<System.Reflection.MethodInfo,System.Reflection.MethodInfo>>","flags":"0x1"},{"name":"staticFieldTypes","type":"System.Type[]","flags":"0x3"},{"name":"staticFields","type":"System.Object[]","flags":"0x3"},{"name":"cctors","type":"System.Int32[]","flags":"0x1"},{"name":"wrappersManager","type":"IFix.Core.WrappersManager","flags":"0x1"},{"name":"Info","type":"System.Action<System.String>","flags":"0x16"},{"name":"<>f__mg$cache0","type":"System.Action<System.String>","flags":"0x11"}],"properties":[{"name":"ExceptionHandlers"},{"name":"ExternTypes"},{"name":"ExternMethods"},{"name":"InternStrings"},{"name":"FieldInfos"},{"name":"NewFieldInfos"},{"name":"AnonymousStoreyInfos"},{"name":"StaticFieldTypes"},{"name":"Cctors"},{"name":"WrappersManager"}],"flags":"0x100001","parent":"Object"},{"name":"WrappersManager","namespace":"IFix.Core","fullName":"IFix.Core.WrappersManager","addr":"0x7602d98570","methods":[{"name":"CreateDelegate","ret":"System.Delegate","params":[{"name":"type","type":"System.Type"},{"name":"id","type":"System.Int32"},{"name":"anon","type":"System.Object"}]},{"name":"CreateBridge","ret":"IFix.Core.AnonymousStorey","params":[{"name":"fieldNum","type":"System.Int32"},{"name":"fieldTypes","type":"System.Int32[]"},{"name":"typeIndex","type":"System.Int32"},{"name":"vTable","type":"System.Int32[]"},{"name":"slots","type":"System.Int32[]"},{"name":"virtualMachine","type":"IFix.Core.VirtualMachine"}]},{"name":"CreateWrapper","rva":"0x187a2fc","addr":"0x768c99e2fc","ret":"System.Object","params":[{"name":"id","type":"System.Int32"}]},{"name":"InitWrapperArray","rva":"0x187a2fc","addr":"0x768c99e2fc","ret":"System.Object","params":[{"name":"len","type":"System.Int32"}]}],"fields":[],"properties":[],"flags":"0xa1"}]}